lulc_validation/__init_.py
lulc_validation/lulc_val.py
lulc_validation-0.0.4.dist-info/LICENSE
lulc_validation-0.0.4.dist-info/METADATA
lulc_validation-0.0.4.dist-info/WHEEL
lulc_validation-0.0.4.dist-info/top_level.txt
lulc_validation-0.0.4.dist-info/RECORD
