Metadata-Version: 2.1
Name: lulc-validation
Version: 0.0.4
Summary: LULC accuracy assessment with reference data generated via stratified sampling
Author: John Duncan
Classifier: License :: OSI Approved :: MIT License
Classifier: Programming Language :: Python
Classifier: Programming Language :: Python :: 3
Requires-Python: >=3.9
License-File: LICENSE
Requires-Dist: requests
Requires-Dist: pandas
Requires-Dist: geopandas
Requires-Dist: shapely
Requires-Dist: rtree
Requires-Dist: fiona
